Metadata-Version: 2.1
Name: odoo13-addon-delivery-preference-glue-stock-picking-group
Version: 13.0.1.0.1.dev10
Summary: Fix Delivery preferences module on grouping picking
Home-page: https://github.com/OCA/wms
Author: Camptocamp,Odoo Community Association (OCA)
Author-email: support@odoo-community.org
License: AGPL-3
Platform: UNKNOWN
Classifier: Programming Language :: Python
Classifier: Framework :: Odoo
Classifier: Framework :: Odoo :: 13.0
Classifier: License :: OSI Approved :: GNU Affero General Public License v3
Requires-Python: >=3.5
Requires-Dist: odoo13-addon-delivery-carrier-preference
Requires-Dist: odoo13-addon-stock-picking-group-by-partner-by-carrier
Requires-Dist: odoo <13.1dev,>=13.0a
